pychemprojections/__init__.py
pychemprojections/fischer/__init__.py
pychemprojections/fischer/__main__.py
pychemprojections/fischer/drawingclasses.py
pychemprojections/fischer/multiplechiral.py
pychemprojections/fischer/singlechiral.py
pychemprojections/fischer/stringmanipulation.py
pychemprojections/fischer/visualization.py
pychemprojections/newman/__init__.py
pychemprojections/newman/__main__.py
pychemprojections/newman/drawingclasses.py
pychemprojections/newman/drawingelements.py
pychemprojections/newman/stringmanipulation.py
pychemprojections/newman/visualization.py
pychemprojections/utils/__init__.py
pychemprojections/utils/logger_utils.py
pychemprojections/utils/rdkit_utils.py
pychemprojections/utils/smiles_manipulation_utils.py
pychemprojections/wedgedash/__init__.py
pychemprojections/wedgedash/__main__.py
pychemprojections/wedgedash/bondoperations.py
pychemprojections/wedgedash/visualization.py
pychemprojections-0.1.0.dist-info/METADATA
pychemprojections-0.1.0.dist-info/WHEEL
pychemprojections-0.1.0.dist-info/licenses/LICENSE.txt
pychemprojections-0.1.0.dist-info/RECORD
